<?xml version="1.0" encoding="UTF-8"?>
<!DOCTYPE mapper PUBLIC "-//mybatis.org//DTD Mapper 3.0//EN" "http://mybatis.org/dtd/mybatis-3-mapper.dtd">
<mapper namespace="com.example.batch.console.mapper.NotificationChannelMapper">

    <select id="selectByTenant" resultType="map">
        SELECT id, tenant_id, channel_code, channel_name, channel_type, config_json,
               enabled, created_by, updated_by, created_at, updated_at
          FROM batch.notification_channel
         WHERE tenant_id = #{tenantId}
         ORDER BY created_at DESC
    </select>

    <select id="selectByCode" resultType="map">
        SELECT id, tenant_id, channel_code, channel_name, channel_type, config_json,
               enabled, created_by, updated_by, created_at, updated_at
          FROM batch.notification_channel
         WHERE tenant_id = #{tenantId} AND channel_code = #{channelCode}
    </select>

    <insert id="insert">
        INSERT INTO batch.notification_channel (tenant_id, channel_code, channel_name, channel_type,
                                                config_json, enabled, created_by, updated_by)
        VALUES (#{tenantId}, #{channelCode}, #{channelName}, #{channelType},
                #{configJson}::jsonb, #{enabled}, #{createdBy}, #{updatedBy})
    </insert>

    <update id="update">
        UPDATE batch.notification_channel
           SET channel_name = #{channelName},
               channel_type = #{channelType},
               config_json = #{configJson}::jsonb,
               enabled = #{enabled},
               updated_by = #{updatedBy},
               updated_at = CURRENT_TIMESTAMP
         WHERE tenant_id = #{tenantId} AND channel_code = #{channelCode}
    </update>

    <delete id="deleteByCode">
        DELETE FROM batch.notification_channel
         WHERE tenant_id = #{tenantId} AND channel_code = #{channelCode}
    </delete>
</mapper>
