<?xml version="1.0" encoding="UTF-8"?>
<!DOCTYPE mapper PUBLIC "-//mybatis.org//DTD Mapper 3.0//EN" "http://mybatis.org/dtd/mybatis-3-mapper.dtd">
<mapper namespace="io.github.pinpols.batch.console.domain.rbac.mapper.TenantMapper">

    <select id="selectByQuery" resultType="map">
        select id, tenant_id, tenant_name, status, description, created_at, updated_at, created_by
        from batch.tenant
        <where>
            <if test="keyword != null and keyword != ''">
                and (tenant_id ilike concat('%', #{keyword}, '%')
                  or tenant_name ilike concat('%', #{keyword}, '%'))
            </if>
            <if test="status != null and status != ''">
                and status = #{status}
            </if>
        </where>
        order by id desc
        <include refid="io.github.pinpols.batch.common.mapper.CommonFragments.offsetPageClause"/>
    </select>

    <select id="countByQuery" resultType="long">
        select count(1)
        from batch.tenant
        <where>
            <if test="keyword != null and keyword != ''">
                and (tenant_id ilike concat('%', #{keyword}, '%')
                  or tenant_name ilike concat('%', #{keyword}, '%'))
            </if>
            <if test="status != null and status != ''">
                and status = #{status}
            </if>
        </where>
    </select>

    <select id="selectByTenantId" resultType="map">
        select id, tenant_id, tenant_name, status, description, created_at, updated_at, created_by
        from batch.tenant
        where tenant_id = #{tenantId}
        limit 1
    </select>

    <!-- R7-A3-P1: 批量按 tenant_id 取，替代 batch create N+1。 -->
    <select id="selectByTenantIds" resultType="map">
        select id, tenant_id, tenant_name, status, description, created_at, updated_at, created_by
        from batch.tenant
        where tenant_id in
            <foreach collection="tenantIds" item="t" open="(" separator="," close=")">
                #{t}
            </foreach>
    </select>

    <insert id="insert" parameterType="io.github.pinpols.batch.console.domain.param.TenantUpsertParam">
        insert into batch.tenant (tenant_id, tenant_name, status, description, created_by)
        values (#{tenantId}, #{tenantName}, #{status}, #{description}, #{createdBy})
    </insert>

    <update id="update">
        update batch.tenant
        set tenant_name = #{tenantName},
            description = #{description},
            updated_at  = current_timestamp
        where tenant_id = #{tenantId}
    </update>

    <update id="updateStatus">
        update batch.tenant
        set status     = #{status},
            updated_at = current_timestamp
        where tenant_id = #{tenantId}
    </update>

</mapper>
